najini/__init__.py
najini/inventory.py
najini-0.1.dist-info/METADATA
najini-0.1.dist-info/WHEEL
najini-0.1.dist-info/top_level.txt
najini-0.1.dist-info/RECORD
