Metadata-Version: 2.1
Name: najini
Version: 0.1
Summary: A collection of python-based tools that connect notion with mongodb.
Author: Joe Easterly
